{
  "style": {
    "touched_dimensions": [
      {
        "dimension": "叙事母题与核心矛盾",
        "boundary": "边界：规则：暗恋的暴露需要通过\"身体比脑子快\"的动作（递毛巾→缩回），不能通过\"我知道你的一切\"的台词。",
        "nature": "违反",
        "reason": "林远亭说\"我最近很爱喝焦糖玛奇朵\"，并主动帮她点焦糖玛奇朵，这属于通过台词暴露他对她的了解（他知道她喜欢焦糖玛奇朵），而不是通过本能动作暴露暗恋。读者会问\"他怎么知道她喜欢焦糖玛奇朵？\"，突破了认知边界。"
      },
      {
        "dimension": "情感表达",
        "boundary": "边界：规则：情感释放必须通过\"不由自主\"的行为，而非\"精心准备\"的行为。",
        "nature": "违反",
        "reason": "他主动帮她拉行李、主动点焦糖玛奇朵，这些行为看起来像是提前策划好的示好，而非一时冲动后缩回。行为需要内心独白解释动机（如\"他为什么知道她喜欢这个口味\"），说明行为本身不够自然。"
      },
      {
        "dimension": "人物塑造",
        "boundary": "边界：规则：林远亭的情感表达上限是\"做了一件出格的事然后缩回\"，不能是\"做了一件出格的事然后解释\"。",
        "nature": "违反",
        "reason": "林远亭主动说出\"我最近很爱喝焦糖玛奇朵\"并帮她点单，这属于主动表达和解释自己的喜好，超出了\"做一件出格的事然后缩回\"的上限，显得他擅长表达感情，违反了\"十年暗恋却不敢表白\"的基础设定。"
      }
    ]
  },
  "motif": {
    "touched_motifs": [
      {
        "motif": "手势",
        "usage": "他帮她拉行李到桌旁，这是一个手势动作，但缺乏\"缩回\"的克制感，显得过于主动。",
        "alignment": "偏离"
      }
    ]
  },
  "story": {
    "touched_characters": [
      {
        "character": "林远亭",
        "behavior_assessment": "主动帮她拉行李、主动点她喜欢的咖啡，行为显得过于主动和擅长追求，不符合\"内向、压抑、不敢表白\"的人物设定。",
        "alignment": "不一致"
      }
    ],
    "touched_tensions": [
      {
        "tension": "暗恋的暴露方式",
        "relevance": "文本点通过台词和主动行为暴露暗恋，而非通过本能动作，与契约要求的\"身体比脑子快\"的暴露方式冲突。"
      }
    ]
  }
}